COPYING
LICENSE
README.md
requirements.txt
setup.py
fnyzer/FNFactory.py
fnyzer/FlexN.py
fnyzer/GFlexN.py
fnyzer/LFlexN.py
fnyzer/MFlexN.py
fnyzer/__init__.py
fnyzer/cobra2fn.py
fnyzer/fnyzer.py
fnyzer/netel.py
fnyzer/ptime.py
fnyzer/regsheap.py
fnyzer.egg-info/PKG-INFO
fnyzer.egg-info/SOURCES.txt
fnyzer.egg-info/dependency_links.txt
fnyzer.egg-info/entry_points.txt
fnyzer.egg-info/requires.txt
fnyzer.egg-info/top_level.txt