Metadata-Version: 2.1
Name: fnyzer
Version: 1.3.10
Summary: Flexible Nets analYZER
Home-page: https://bitbucket.org/Julvez/fnyzer
Author: Jorge Julvez
Author-email: fnyzer@unizar.es
License: GNU GENERAL PUBLIC LICENSE
Keywords: flexible nets analyzer
License-File: LICENSE
License-File: COPYING
Requires-Dist: pyomo>=6.8.2
Requires-Dist: numpy>=2.1.0
Requires-Dist: xlwt>=1.3.0
Requires-Dist: matplotlib>=3.0.0
Requires-Dist: statsmodels>=0.10.1
